setup.py
brightcove/__init__.py
brightcove/api.py
brightcove/core.py
brightcove/objects.py
brightcove/utils.py
brightcove.egg-info/PKG-INFO
brightcove.egg-info/SOURCES.txt
brightcove.egg-info/dependency_links.txt
brightcove.egg-info/top_level.txt
tests/__init__.py
tests/test_api.py
tests/test_core.py
tests/test_decorators.py
tests/test_objects.py
tests/utils.py