Metadata-Version: 1.0
Name: brightcove
Version: 0.2
Summary: A python wrapper for the Brightcove read-only API.
Home-page: UNKNOWN
Author: Jonathan Beluch
Author-email: web@jonathanbeluch.com
License: GPL3
Keywords: python brightcove api
Platform: UNKNOWN
Classifier: Development Status :: 3 - Alpha
Classifier: Topic :: Utilities
Classifier: License :: OSI Approved :: GNU Affero General Public License v3
Classifier: Programming Language :: Python
